{
    "ammo": [
      {
        "caliber": "Caliber556x45NATO",
        "damage": 57,
        "penetrationPower": 31,
        "armorDamage": 37,
        "accuracyModifier": 0,
        "recoilModifier": 0,
        "lightBleedModifier": 0,
        "heavyBleedModifier": 0,
        "fragmentationChance": 0.5,
        "initialSpeed": 922,
        "tracer": false,
        "tracerColor": "red",
        "ammoType": "bullet",
        "projectileCount": 1
      },
      {
        "caliber": "Caliber556x45NATO",
        "damage": 49,
        "penetrationPower": 44,
        "armorDamage": 47,
        "accuracyModifier": -0.05,
        "recoilModifier": 0.05,
        "lightBleedModifier": 0,
        "heavyBleedModifier": 0,
        "fragmentationChance": 0.44,
        "initialSpeed": 945,
        "tracer": false,
        "tracerColor": "red",
        "ammoType": "bullet",
        "projectileCount": 1
      },
      {
        "caliber": "Caliber12g",
        "damage": 39,
        "penetrationPower": 3,
        "armorDamage": 26,
        "accuracyModifier": 0,
        "recoilModifier": 0,
        "lightBleedModifier": 0,
        "heavyBleedModifier": 0,
        "fragmentationChance": 0,
        "initialSpeed": 415,
        "tracer": false,
        "tracerColor": "red",
        "ammoType": "buckshot",
        "projectileCount": 8
      },
      {
        "caliber": "Caliber762x54R",
        "damage": 75,
        "penetrationPower": 62,
        "armorDamage": 87,
        "accuracyModifier": 0,
        "recoilModifier": 0.1,
        "lightBleedModifier": 0,
        "heavyBleedModifier": 0,
        "fragmentationChance": 0.08,
        "initialSpeed": 875,
        "tracer": false,
        "tracerColor": "red",
        "ammoType": "bullet",
        "projectileCount": 1
      },
      {
        "caliber": "Caliber762x39",
        "damage": 57,
        "penetrationPower": 35,
        "armorDamage": 52,
        "accuracyModifier": 0,
        "recoilModifier": 0,
        "lightBleedModifier": 0,
        "heavyBleedModifier": 0,
        "fragmentationChance": 0.2,
        "initialSpeed": 717,
        "tracer": false,
        "tracerColor": "red",
        "ammoType": "bullet",
        "projectileCount": 1
      },
      {
        "caliber": "Caliber40mmRU",
        "damage": 199,
        "penetrationPower": 0,
        "armorDamage": 68,
        "accuracyModifier": 0,
        "recoilModifier": 0,
        "lightBleedModifier": 0,
        "heavyBleedModifier": 0,
        "fragmentationChance": 0,
        "initialSpeed": 76,
        "tracer": false,
        "tracerColor": "red",
        "ammoType": "grenade",
        "projectileCount": 1
      },
      {
        "caliber": "Caliber9x19PARA",
        "damage": 54,
        "penetrationPower": 20,
        "armorDamage": 33,
        "accuracyModifier": 0,
        "recoilModifier": 0,
        "lightBleedModifier": 0,
        "heavyBleedModifier": 0,
        "fragmentationChance": 0.15,
        "initialSpeed": 457,
        "tracer": false,
        "tracerColor": "red",
        "ammoType": "bullet",
        "projectileCount": 1
      },
      {
        "caliber": "Caliber545x39",
        "damage": 46,
        "penetrationPower": 45,
        "armorDamage": 46,
        "accuracyModifier": -0.03,
        "recoilModifier": 0.07,
        "lightBleedModifier": 0,
        "heavyBleedModifier": 0,
        "fragmentationChance": 0.16,
        "initialSpeed": 890,
        "tracer": false,
        "tracerColor": "red",
        "ammoType": "bullet",
        "projectileCount": 1
      },
      {
        "caliber": "Caliber545x39",
        "damage": 43,
        "penetrationPower": 54,
        "armorDamage": 57,
        "accuracyModifier": -0.04,
        "recoilModifier": 0.1,
        "lightBleedModifier": 0,
        "heavyBleedModifier": 0,
        "fragmentationChance": 0.17,
        "initialSpeed": 830,
        "tracer": false,
        "tracerColor": "red",
        "ammoType": "bullet",
        "projectileCount": 1
      },
      {
        "caliber": "Caliber545x39",
        "damage": 48,
        "penetrationPower": 37,
        "armorDamage": 44,
        "accuracyModifier": -0.04,
        "recoilModifier": 0.05,
        "lightBleedModifier": 0,
        "heavyBleedModifier": 0,
        "fragmentationChance": 0.164,
        "initialSpeed": 880,
        "tracer": true,
        "tracerColor": "tracerRed",
        "ammoType": "bullet",
        "projectileCount": 1
      },
      {
        "caliber": "Caliber545x39",
        "damage": 55,
        "penetrationPower": 24,
        "armorDamage": 38,
        "accuracyModifier": 0,
        "recoilModifier": 0,
        "lightBleedModifier": 0,
        "heavyBleedModifier": 0,
        "fragmentationChance": 0.25,
        "initialSpeed": 884,
        "tracer": false,
        "tracerColor": "red",
        "ammoType": "bullet",
        "projectileCount": 1
      },
      {
        "caliber": "Caliber545x39",
        "damage": 76,
        "penetrationPower": 9,
        "armorDamage": 15,
        "accuracyModifier": 0.03,
        "recoilModifier": -0.03,
        "lightBleedModifier": 0.15,
        "heavyBleedModifier": 0.15,
        "fragmentationChance": 0.35,
        "initialSpeed": 884,
        "tracer": false,
        "tracerColor": "red",
        "ammoType": "bullet",
        "projectileCount": 1
      },
      {
        "caliber": "Caliber545x39",
        "damage": 50,
        "penetrationPower": 34,
        "armorDamage": 42,
        "accuracyModifier": -0.02,
        "recoilModifier": 0.03,
        "lightBleedModifier": 0,
        "heavyBleedModifier": 0,
        "fragmentationChance": 0.17,
        "initialSpeed": 886,
        "tracer": false,
        "tracerColor": "red",
        "ammoType": "bullet",
        "projectileCount": 1
      },
      {
        "caliber": "Caliber545x39",
        "damage": 70,
        "penetrationPower": 13,
        "armorDamage": 24,
        "accuracyModifier": 0,
        "recoilModifier": -0.05,
        "lightBleedModifier": 0,
        "heavyBleedModifier": 0,
        "fragmentationChance": 0.3,
        "initialSpeed": 866,
        "tracer": false,
        "tracerColor": "red",
        "ammoType": "bullet",
        "projectileCount": 1
      },
      {
        "caliber": "Caliber545x39",
        "damage": 53,
        "penetrationPower": 28,
        "armorDamage": 40,
        "accuracyModifier": 0,
        "recoilModifier": 0,
        "lightBleedModifier": 0,
        "heavyBleedModifier": 0,
        "fragmentationChance": 0.4,
        "initialSpeed": 890,
        "tracer": false,
        "tracerColor": "red",
        "ammoType": "bullet",
        "projectileCount": 1
      },
      {
        "caliber": "Caliber545x39",
        "damage": 65,
        "penetrationPower": 15,
        "armorDamage": 31,
        "accuracyModifier": 0.05,
        "recoilModifier": -0.05,
        "lightBleedModifier": 0.1,
        "heavyBleedModifier": 0.1,
        "fragmentationChance": 0.45,
        "initialSpeed": 873,
        "tracer": false,
        "tracerColor": "red",
        "ammoType": "bullet",
        "projectileCount": 1
      },
      {
        "caliber": "Caliber545x39",
        "damage": 57,
        "penetrationPower": 20,
        "armorDamage": 36,
        "accuracyModifier": -0.03,
        "recoilModifier": 0,
        "lightBleedModifier": 0,
        "heavyBleedModifier": 0,
        "fragmentationChance": 0.16,
        "initialSpeed": 883,
        "tracer": true,
        "tracerColor": "tracerRed",
        "ammoType": "bullet",
        "projectileCount": 1
      },
      {
        "caliber": "Caliber545x39",
        "damage": 63,
        "penetrationPower": 17,
        "armorDamage": 33,
        "accuracyModifier": 0,
        "recoilModifier": -0.15,
        "lightBleedModifier": 0,
        "heavyBleedModifier": 0,
        "fragmentationChance": 0.1,
        "initialSpeed": 303,
        "tracer": false,
        "tracerColor": "red",
        "ammoType": "bullet",
        "projectileCount": 1
      },
      {
        "caliber": "Caliber762x25TT",
        "damage": 58,
        "penetrationPower": 12,
        "armorDamage": 32,
        "accuracyModifier": 0.15,
        "recoilModifier": -0.15,
        "lightBleedModifier": 0,
        "heavyBleedModifier": 0,
        "fragmentationChance": 0.25,
        "initialSpeed": 425,
        "tracer": false,
        "tracerColor": "red",
        "ammoType": "bullet",
        "projectileCount": 1
      },
      {
        "caliber": "Caliber762x25TT",
        "damage": 60,
        "penetrationPower": 11,
        "armorDamage": 29,
        "accuracyModifier": 0,
        "recoilModifier": 0,
        "lightBleedModifier": 0,
        "heavyBleedModifier": 0,
        "fragmentationChance": 0.25,
        "initialSpeed": 427,
        "tracer": false,
        "tracerColor": "red",
        "ammoType": "bullet",
        "projectileCount": 1
      },
      {
        "caliber": "Caliber762x25TT",
        "damage": 64,
        "penetrationPower": 8,
        "armorDamage": 28,
        "accuracyModifier": 0.05,
        "recoilModifier": -0.05,
        "lightBleedModifier": 0.15,
        "heavyBleedModifier": 0.1,
        "fragmentationChance": 0.35,
        "initialSpeed": 375,
        "tracer": false,
        "tracerColor": "red",
        "ammoType": "bullet",
        "projectileCount": 1
      },
      {
        "caliber": "Caliber762x25TT",
        "damage": 66,
        "penetrationPower": 7,
        "armorDamage": 27,
        "accuracyModifier": 0.1,
        "recoilModifier": -0.1,
        "lightBleedModifier": 0.15,
        "heavyBleedModifier": 0.1,
        "fragmentationChance": 0.35,
        "initialSpeed": 385,
        "tracer": false,
        "tracerColor": "red",
        "ammoType": "bullet",
        "projectileCount": 1
      },
      {
        "caliber": "Caliber762x25TT",
        "damage": 58,
        "penetrationPower": 14,
        "armorDamage": 32,
        "accuracyModifier": 0,
        "recoilModifier": 0,
        "lightBleedModifier": 0,
        "heavyBleedModifier": 0,
        "fragmentationChance": 0.25,
        "initialSpeed": 430,
        "tracer": false,
        "tracerColor": "red",
        "ammoType": "bullet",
        "projectileCount": 1
      },
      {
        "caliber": "Caliber762x25TT",
        "damage": 50,
        "penetrationPower": 25,
        "armorDamage": 36,
        "accuracyModifier": 0,
        "recoilModifier": 0,
        "lightBleedModifier": 0,
        "heavyBleedModifier": 0,
        "fragmentationChance": 0.2,
        "initialSpeed": 430,
        "tracer": false,
        "tracerColor": "red",
        "ammoType": "bullet",
        "projectileCount": 1
      },
      {
        "caliber": "Caliber762x25TT",
        "damage": 55,
        "penetrationPower": 18,
        "armorDamage": 34,
        "accuracyModifier": -0.1,
        "recoilModifier": 0,
        "lightBleedModifier": 0,
        "heavyBleedModifier": 0,
        "fragmentationChance": 0.166,
        "initialSpeed": 415,
        "tracer": true,
        "tracerColor": "tracerRed",
        "ammoType": "bullet",
        "projectileCount": 1
      },
      {
        "caliber": "Caliber9x18PM",
        "damage": 53,
        "penetrationPower": 18,
        "armorDamage": 28,
        "accuracyModifier": 0,
        "recoilModifier": 0,
        "lightBleedModifier": 0.15,
        "heavyBleedModifier": 0.1,
        "fragmentationChance": 0.17,
        "initialSpeed": 325,
        "tracer": false,
        "tracerColor": "red",
        "ammoType": "bullet",
        "projectileCount": 1
      },
      {
        "caliber": "Caliber9x18PM",
        "damage": 50,
        "penetrationPower": 5,
        "armorDamage": 16,
        "accuracyModifier": 0,
        "recoilModifier": 0,
        "lightBleedModifier": 0.1,
        "heavyBleedModifier": 0,
        "fragmentationChance": 0.25,
        "initialSpeed": 302,
        "tracer": false,
        "tracerColor": "red",
        "ammoType": "bullet",
        "projectileCount": 1
      },
      {
        "caliber": "Caliber9x18PM",
        "damage": 40,
        "penetrationPower": 28,
        "armorDamage": 30,
        "accuracyModifier": 0,
        "recoilModifier": 0.04,
        "lightBleedModifier": 0,
        "heavyBleedModifier": 0,
        "fragmentationChance": 0.16,
        "initialSpeed": 519,
        "tracer": false,
        "tracerColor": "red",
        "ammoType": "bullet",
        "projectileCount": 1
      },
      {
        "caliber": "Caliber9x18PM",
        "damage": 58,
        "penetrationPower": 24,
        "armorDamage": 33,
        "accuracyModifier": 0,
        "recoilModifier": 0.05,
        "lightBleedModifier": 0,
        "heavyBleedModifier": 0,
        "fragmentationChance": 0.17,
        "initialSpeed": 420,
        "tracer": false,
        "tracerColor": "red",
        "ammoType": "bullet",
        "projectileCount": 1
      },
      {
        "caliber": "Caliber9x18PM",
        "damage": 61,
        "penetrationPower": 7,
        "armorDamage": 15,
        "accuracyModifier": 0,
        "recoilModifier": 0,
        "lightBleedModifier": 0.15,
        "heavyBleedModifier": 0,
        "fragmentationChance": 0.35,
        "initialSpeed": 297,
        "tracer": false,
        "tracerColor": "red",
        "ammoType": "bullet",
        "projectileCount": 1
      },
      {
        "caliber": "Caliber9x18PM",
        "damage": 59,
        "penetrationPower": 8,
        "armorDamage": 22,
        "accuracyModifier": -0.05,
        "recoilModifier": -0.07,
        "lightBleedModifier": 0.15,
        "heavyBleedModifier": 0,
        "fragmentationChance": 0.166,
        "initialSpeed": 301,
        "tracer": true,
        "tracerColor": "red",
        "ammoType": "bullet",
        "projectileCount": 1
      },
      {
        "caliber": "Caliber9x18PM",
        "damage": 58,
        "penetrationPower": 6,
        "armorDamage": 16,
        "accuracyModifier": 0,
        "recoilModifier": 0,
        "lightBleedModifier": 0.15,
        "heavyBleedModifier": 0,
        "fragmentationChance": 0.3,
        "initialSpeed": 302,
        "tracer": false,
        "tracerColor": "red",
        "ammoType": "bullet",
        "projectileCount": 1
      },
      {
        "caliber": "Caliber9x18PM",
        "damage": 55,
        "penetrationPower": 6,
        "armorDamage": 16,
        "accuracyModifier": 0,
        "recoilModifier": 0,
        "lightBleedModifier": 0.15,
        "heavyBleedModifier": 0,
        "fragmentationChance": 0.25,
        "initialSpeed": 330,
        "tracer": false,
        "tracerColor": "red",
        "ammoType": "bullet",
        "projectileCount": 1
      },
      {
        "caliber": "Caliber9x18PM",
        "damage": 54,
        "penetrationPower": 5,
        "armorDamage": 13,
        "accuracyModifier": 0.1,
        "recoilModifier": 0,
        "lightBleedModifier": 0.15,
        "heavyBleedModifier": 0,
        "fragmentationChance": 0.35,
        "initialSpeed": 315,
        "tracer": false,
        "tracerColor": "red",
        "ammoType": "bullet",
        "projectileCount": 1
      },
      {
        "caliber": "Caliber9x18PM",
        "damage": 50,
        "penetrationPower": 12,
        "armorDamage": 26,
        "accuracyModifier": 0,
        "recoilModifier": 0,
        "lightBleedModifier": 0,
        "heavyBleedModifier": 0,
        "fragmentationChance": 0.2,
        "initialSpeed": 298,
        "tracer": false,
        "tracerColor": "red",
        "ammoType": "bullet",
        "projectileCount": 1
      },
      {
        "caliber": "Caliber9x18PM",
        "damage": 69,
        "penetrationPower": 3,
        "armorDamage": 5,
        "accuracyModifier": 0,
        "recoilModifier": 0,
        "lightBleedModifier": 0.1,
        "heavyBleedModifier": 0,
        "fragmentationChance": 0.4,
        "initialSpeed": 280,
        "tracer": false,
        "tracerColor": "red",
        "ammoType": "bullet",
        "projectileCount": 1
      },
      {
        "caliber": "Caliber9x18PM",
        "damage": 65,
        "penetrationPower": 13,
        "armorDamage": 26,
        "accuracyModifier": 0,
        "recoilModifier": 0,
        "lightBleedModifier": 0,
        "heavyBleedModifier": 0,
        "fragmentationChance": 0.02,
        "initialSpeed": 330,
        "tracer": false,
        "tracerColor": "red",
        "ammoType": "bullet",
        "projectileCount": 1
      },
      {
        "caliber": "Caliber9x18PM",
        "damage": 77,
        "penetrationPower": 2,
        "armorDamage": 5,
        "accuracyModifier": 0,
        "recoilModifier": 0,
        "lightBleedModifier": 0.25,
        "heavyBleedModifier": 0.1,
        "fragmentationChance": 0.02,
        "initialSpeed": 420,
        "tracer": false,
        "tracerColor": "red",
        "ammoType": "bullet",
        "projectileCount": 1
      },
      {
        "caliber": "Caliber9x18PM",
        "damage": 67,
        "penetrationPower": 1,
        "armorDamage": 2,
        "accuracyModifier": 0,
        "recoilModifier": 0,
        "lightBleedModifier": 0.15,
        "heavyBleedModifier": 0.1,
        "fragmentationChance": 0.6,
        "initialSpeed": 250,
        "tracer": false,
        "tracerColor": "red",
        "ammoType": "bullet",
        "projectileCount": 1
      },
      {
        "caliber": "Caliber9x39",
        "damage": 71,
        "penetrationPower": 28,
        "armorDamage": 39,
        "accuracyModifier": 0,
        "recoilModifier": 0,
        "lightBleedModifier": 0,
        "heavyBleedModifier": 0.1,
        "fragmentationChance": 0.2,
        "initialSpeed": 290,
        "tracer": false,
        "tracerColor": "red",
        "ammoType": "bullet",
        "projectileCount": 1
      },
      {
        "caliber": "Caliber9x39",
        "damage": 60,
        "penetrationPower": 48,
        "armorDamage": 64,
        "accuracyModifier": 0,
        "recoilModifier": 0.05,
        "lightBleedModifier": 0.1,
        "heavyBleedModifier": 0.1,
        "fragmentationChance": 0.1,
        "initialSpeed": 305,
        "tracer": false,
        "tracerColor": "red",
        "ammoType": "bullet",
        "projectileCount": 1
      },
      {
        "caliber": "Caliber12g",
        "damage": 167,
        "penetrationPower": 15,
        "armorDamage": 55,
        "accuracyModifier": 1.2,
        "recoilModifier": 0,
        "lightBleedModifier": 0.1,
        "heavyBleedModifier": 0.15,
        "fragmentationChance": 0.2,
        "initialSpeed": 370,
        "tracer": false,
        "tracerColor": "red",
        "ammoType": "bullet",
        "projectileCount": 1
      },
      {
        "caliber": "Caliber9x19PARA",
        "damage": 59,
        "penetrationPower": 10,
        "armorDamage": 32,
        "accuracyModifier": 0,
        "recoilModifier": 0,
        "lightBleedModifier": 0,
        "heavyBleedModifier": 0,
        "fragmentationChance": 0.25,
        "initialSpeed": 340,
        "tracer": false,
        "tracerColor": "red",
        "ammoType": "bullet",
        "projectileCount": 1
      },
      {
        "caliber": "Caliber762x54R",
        "damage": 81,
        "penetrationPower": 42,
        "armorDamage": 78,
        "accuracyModifier": -0.05,
        "recoilModifier": 0,
        "lightBleedModifier": 0,
        "heavyBleedModifier": 0,
        "fragmentationChance": 0.18,
        "initialSpeed": 865,
        "tracer": false,
        "tracerColor": "red",
        "ammoType": "bullet",
        "projectileCount": 1
      },
      {
        "caliber": "Caliber762x51",
        "damage": 80,
        "penetrationPower": 41,
        "armorDamage": 66,
        "accuracyModifier": 0,
        "recoilModifier": 0,
        "lightBleedModifier": 0,
        "heavyBleedModifier": 0,
        "fragmentationChance": 0.17,
        "initialSpeed": 833,
        "tracer": false,
        "tracerColor": "red",
        "ammoType": "bullet",
        "projectileCount": 1
      },
      {
        "caliber": "Caliber762x39",
        "damage": 58,
        "penetrationPower": 47,
        "armorDamage": 63,
        "accuracyModifier": -0.03,
        "recoilModifier": 0.07,
        "lightBleedModifier": 0,
        "heavyBleedModifier": 0,
        "fragmentationChance": 0.12,
        "initialSpeed": 730,
        "tracer": false,
        "tracerColor": "red",
        "ammoType": "bullet",
        "projectileCount": 1
      },
      {
        "caliber": "Caliber762x39",
        "damage": 64,
        "penetrationPower": 30,
        "armorDamage": 46,
        "accuracyModifier": -0.04,
        "recoilModifier": -0.06,
        "lightBleedModifier": 0,
        "heavyBleedModifier": 0,
        "fragmentationChance": 0.12,
        "initialSpeed": 720,
        "tracer": true,
        "tracerColor": "red",
        "ammoType": "bullet",
        "projectileCount": 1
      },
      {
        "caliber": "Caliber762x39",
        "damage": 56,
        "penetrationPower": 29,
        "armorDamage": 42,
        "accuracyModifier": 0.05,
        "recoilModifier": -0.3,
        "lightBleedModifier": 0,
        "heavyBleedModifier": 0,
        "fragmentationChance": 0.075,
        "initialSpeed": 301,
        "tracer": false,
        "tracerColor": "red",
        "ammoType": "bullet",
        "projectileCount": 1
      },
      {
        "caliber": "Caliber762x39",
        "damage": 87,
        "penetrationPower": 15,
        "armorDamage": 20,
        "accuracyModifier": -0.05,
        "recoilModifier": 0.05,
        "lightBleedModifier": 0.15,
        "heavyBleedModifier": 0.15,
        "fragmentationChance": 0.4,
        "initialSpeed": 754,
        "tracer": false,
        "tracerColor": "red",
        "ammoType": "bullet",
        "projectileCount": 1
      },
      {
        "caliber": "Caliber366TKM",
        "damage": 98,
        "penetrationPower": 23,
        "armorDamage": 48,
        "accuracyModifier": 0,
        "recoilModifier": 0.1,
        "lightBleedModifier": 0.2,
        "heavyBleedModifier": 0.25,
        "fragmentationChance": 0.25,
        "initialSpeed": 580,
        "tracer": false,
        "tracerColor": "red",
        "ammoType": "bullet",
        "projectileCount": 1
      },
      {
        "caliber": "Caliber366TKM",
        "damage": 73,
        "penetrationPower": 30,
        "armorDamage": 40,
        "accuracyModifier": -0.1,
        "recoilModifier": -0.15,
        "lightBleedModifier": 0,
        "heavyBleedModifier": 0.2,
        "fragmentationChance": 0.2,
        "initialSpeed": 770,
        "tracer": false,
        "tracerColor": "red",
        "ammoType": "bullet",
        "projectileCount": 1
      },
      {
        "caliber": "Caliber366TKM",
        "damage": 110,
        "penetrationPower": 14,
        "armorDamage": 38,
        "accuracyModifier": 0,
        "recoilModifier": 0,
        "lightBleedModifier": 0.3,
        "heavyBleedModifier": 0.1,
        "fragmentationChance": 0.45,
        "initialSpeed": 550,
        "tracer": false,
        "tracerColor": "red",
        "ammoType": "bullet",
        "projectileCount": 1
      },
      {
        "caliber": "Caliber556x45NATO",
        "damage": 64,
        "penetrationPower": 18,
        "armorDamage": 26,
        "accuracyModifier": -0.02,
        "recoilModifier": -0.02,
        "lightBleedModifier": 0,
        "heavyBleedModifier": 0,
        "fragmentationChance": 0.328,
        "initialSpeed": 874,
        "tracer": true,
        "tracerColor": "red",
        "ammoType": "bullet",
        "projectileCount": 1
      },
      {
        "caliber": "Caliber556x45NATO",
        "damage": 52,
        "penetrationPower": 38,
        "armorDamage": 44,
        "accuracyModifier": -0.04,
        "recoilModifier": 0.04,
        "lightBleedModifier": 0,
        "heavyBleedModifier": 0,
        "fragmentationChance": 0.428,
        "initialSpeed": 940,
        "tracer": true,
        "tracerColor": "red",
        "ammoType": "bullet",
        "projectileCount": 1
      },
      {
        "caliber": "Caliber556x45NATO",
        "damage": 42,
        "penetrationPower": 53,
        "armorDamage": 52,
        "accuracyModifier": -0.07,
        "recoilModifier": 0.08,
        "lightBleedModifier": 0,
        "heavyBleedModifier": 0,
        "fragmentationChance": 0.42,
        "initialSpeed": 1013,
        "tracer": false,
        "tracerColor": "red",
        "ammoType": "bullet",
        "projectileCount": 1
      },
      {
        "caliber": "Caliber556x45NATO",
        "damage": 72,
        "penetrationPower": 11,
        "armorDamage": 24,
        "accuracyModifier": 0,
        "recoilModifier": 0,
        "lightBleedModifier": 0,
        "heavyBleedModifier": 0,
        "fragmentationChance": 0.03,
        "initialSpeed": 936,
        "tracer": false,
        "tracerColor": "red",
        "ammoType": "bullet",
        "projectileCount": 1
      },
      {
        "caliber": "Caliber556x45NATO",
        "damage": 59,
        "penetrationPower": 23,
        "armorDamage": 33,
        "accuracyModifier": 0,
        "recoilModifier": 0,
        "lightBleedModifier": 0,
        "heavyBleedModifier": 0,
        "fragmentationChance": 0.5,
        "initialSpeed": 957,
        "tracer": false,
        "tracerColor": "red",
        "ammoType": "bullet",
        "projectileCount": 1
      },
      {
        "caliber": "Caliber556x45NATO",
        "damage": 79,
        "penetrationPower": 7,
        "armorDamage": 22,
        "accuracyModifier": 0,
        "recoilModifier": 0,
        "lightBleedModifier": 0.15,
        "heavyBleedModifier": 0.15,
        "fragmentationChance": 0.7,
        "initialSpeed": 947,
        "tracer": false,
        "tracerColor": "red",
        "ammoType": "bullet",
        "projectileCount": 1
      },
      {
        "caliber": "Caliber762x54R",
        "damage": 84,
        "penetrationPower": 45,
        "armorDamage": 84,
        "accuracyModifier": 0.1,
        "recoilModifier": 0.08,
        "lightBleedModifier": 0,
        "heavyBleedModifier": 0,
        "fragmentationChance": 0.083,
        "initialSpeed": 875,
        "tracer": false,
        "tracerColor": "red",
        "ammoType": "bullet",
        "projectileCount": 1
      },
      {
        "caliber": "Caliber9x21",
        "damage": 54,
        "penetrationPower": 22,
        "armorDamage": 39,
        "accuracyModifier": 0,
        "recoilModifier": 0,
        "lightBleedModifier": 0,
        "heavyBleedModifier": 0,
        "fragmentationChance": 0.2,
        "initialSpeed": 410,
        "tracer": false,
        "tracerColor": "red",
        "ammoType": "bullet",
        "projectileCount": 1
      },
      {
        "caliber": "Caliber9x21",
        "damage": 65,
        "penetrationPower": 18,
        "armorDamage": 44,
        "accuracyModifier": 0.01,
        "recoilModifier": -0.03,
        "lightBleedModifier": 0.15,
        "heavyBleedModifier": 0.1,
        "fragmentationChance": 0.3,
        "initialSpeed": 413,
        "tracer": false,
        "tracerColor": "red",
        "ammoType": "bullet",
        "projectileCount": 1
      },
      {
        "caliber": "Caliber9x21",
        "damage": 80,
        "penetrationPower": 15,
        "armorDamage": 63,
        "accuracyModifier": 0.03,
        "recoilModifier": -0.05,
        "lightBleedModifier": 0.15,
        "heavyBleedModifier": 0.1,
        "fragmentationChance": 0.35,
        "initialSpeed": 415,
        "tracer": false,
        "tracerColor": "red",
        "ammoType": "bullet",
        "projectileCount": 1
      },
      {
        "caliber": "Caliber9x21",
        "damage": 49,
        "penetrationPower": 32,
        "armorDamage": 42,
        "accuracyModifier": -0.05,
        "recoilModifier": 0.05,
        "lightBleedModifier": 0,
        "heavyBleedModifier": 0,
        "fragmentationChance": 0.2,
        "initialSpeed": 410,
        "tracer": true,
        "tracerColor": "red",
        "ammoType": "bullet",
        "projectileCount": 1
      },
      {
        "caliber": "Caliber20g",
        "damage": 25,
        "penetrationPower": 3,
        "armorDamage": 14,
        "accuracyModifier": 0,
        "recoilModifier": 0,
        "lightBleedModifier": 0,
        "heavyBleedModifier": 0,
        "fragmentationChance": 0,
        "initialSpeed": 430,
        "tracer": false,
        "tracerColor": "red",
        "ammoType": "buckshot",
        "projectileCount": 8
      },
      {
        "caliber": "Caliber9x19PARA",
        "damage": 70,
        "penetrationPower": 10,
        "armorDamage": 38,
        "accuracyModifier": 0,
        "recoilModifier": 0,
        "lightBleedModifier": 0.2,
        "heavyBleedModifier": 0.2,
        "fragmentationChance": 0.25,
        "initialSpeed": 420,
        "tracer": false,
        "tracerColor": "red",
        "ammoType": "bullet",
        "projectileCount": 1
      },
      {
        "caliber": "Caliber762x51",
        "damage": 70,
        "penetrationPower": 64,
        "armorDamage": 83,
        "accuracyModifier": 0.03,
        "recoilModifier": 0.1,
        "lightBleedModifier": 0,
        "heavyBleedModifier": 0,
        "fragmentationChance": 0.13,
        "initialSpeed": 849,
        "tracer": false,
        "tracerColor": "red",
        "ammoType": "bullet",
        "projectileCount": 1
      },
      {
        "caliber": "Caliber762x51",
        "damage": 79,
        "penetrationPower": 44,
        "armorDamage": 75,
        "accuracyModifier": -0.06,
        "recoilModifier": -0.01,
        "lightBleedModifier": 0,
        "heavyBleedModifier": 0,
        "fragmentationChance": 0.14,
        "initialSpeed": 816,
        "tracer": true,
        "tracerColor": "green",
        "ammoType": "bullet",
        "projectileCount": 1
      },
      {
        "caliber": "Caliber46x30",
        "damage": 43,
        "penetrationPower": 40,
        "armorDamage": 41,
        "accuracyModifier": 0,
        "recoilModifier": 0,
        "lightBleedModifier": 0,
        "heavyBleedModifier": 0,
        "fragmentationChance": 0.2,
        "initialSpeed": 620,
        "tracer": false,
        "tracerColor": "red",
        "ammoType": "bullet",
        "projectileCount": 1
      },
      {
        "caliber": "Caliber46x30",
        "damage": 65,
        "penetrationPower": 18,
        "armorDamage": 28,
        "accuracyModifier": 0,
        "recoilModifier": 0,
        "lightBleedModifier": 0,
        "heavyBleedModifier": 0,
        "fragmentationChance": 0.5,
        "initialSpeed": 690,
        "tracer": false,
        "tracerColor": "red",
        "ammoType": "bullet",
        "projectileCount": 1
      },
      {
        "caliber": "Caliber46x30",
        "damage": 35,
        "penetrationPower": 53,
        "armorDamage": 46,
        "accuracyModifier": 0,
        "recoilModifier": 0.1,
        "lightBleedModifier": 0,
        "heavyBleedModifier": 0,
        "fragmentationChance": 0.1,
        "initialSpeed": 680,
        "tracer": false,
        "tracerColor": "red",
        "ammoType": "bullet",
        "projectileCount": 1
      },
      {
        "caliber": "Caliber46x30",
        "damage": 52,
        "penetrationPower": 23,
        "armorDamage": 33,
        "accuracyModifier": 0.1,
        "recoilModifier": -0.22,
        "lightBleedModifier": 0,
        "heavyBleedModifier": 0,
        "fragmentationChance": 0.2,
        "initialSpeed": 290,
        "tracer": false,
        "tracerColor": "red",
        "ammoType": "bullet",
        "projectileCount": 1
      },
      {
        "caliber": "Caliber9x19PARA",
        "damage": 102,
        "penetrationPower": 2,
        "armorDamage": 11,
        "accuracyModifier": 0,
        "recoilModifier": 0.05,
        "lightBleedModifier": 0.3,
        "heavyBleedModifier": 0.1,
        "fragmentationChance": 1,
        "initialSpeed": 381,
        "tracer": false,
        "tracerColor": "red",
        "ammoType": "bullet",
        "projectileCount": 1
      },
      {
        "caliber": "Caliber12g",
        "damage": 265,
        "penetrationPower": 2,
        "armorDamage": 11,
        "accuracyModifier": 0.8,
        "recoilModifier": 0.35,
        "lightBleedModifier": 0.4,
        "heavyBleedModifier": 0.25,
        "fragmentationChance": 1,
        "initialSpeed": 410,
        "tracer": false,
        "tracerColor": "red",
        "ammoType": "bullet",
        "projectileCount": 1
      },
      {
        "caliber": "Caliber556x45NATO",
        "damage": 88,
        "penetrationPower": 3,
        "armorDamage": 11,
        "accuracyModifier": 0.1,
        "recoilModifier": 0.1,
        "lightBleedModifier": 0.2,
        "heavyBleedModifier": 0.2,
        "fragmentationChance": 0.9,
        "initialSpeed": 936,
        "tracer": false,
        "tracerColor": "red",
        "ammoType": "bullet",
        "projectileCount": 1
      },
      {
        "caliber": "Caliber545x39",
        "damage": 37,
        "penetrationPower": 62,
        "armorDamage": 59,
        "accuracyModifier": -0.05,
        "recoilModifier": 0.15,
        "lightBleedModifier": 0,
        "heavyBleedModifier": 0,
        "fragmentationChance": 0.02,
        "initialSpeed": 905,
        "tracer": false,
        "tracerColor": "red",
        "ammoType": "bullet",
        "projectileCount": 1
      },
      {
        "caliber": "Caliber9x39",
        "damage": 68,
        "penetrationPower": 35,
        "armorDamage": 48,
        "accuracyModifier": 0.1,
        "recoilModifier": 0.07,
        "lightBleedModifier": 0.1,
        "heavyBleedModifier": 0.2,
        "fragmentationChance": 0.2,
        "initialSpeed": 310,
        "tracer": false,
        "tracerColor": "red",
        "ammoType": "bullet",
        "projectileCount": 1
      },
      {
        "caliber": "Caliber9x39",
        "damage": 58,
        "penetrationPower": 54,
        "armorDamage": 69,
        "accuracyModifier": 0.1,
        "recoilModifier": 0.15,
        "lightBleedModifier": 0,
        "heavyBleedModifier": 0,
        "fragmentationChance": 0.1,
        "initialSpeed": 295,
        "tracer": false,
        "tracerColor": "red",
        "ammoType": "bullet",
        "projectileCount": 1
      },
      {
        "caliber": "Caliber9x19PARA",
        "damage": 58,
        "penetrationPower": 14,
        "armorDamage": 33,
        "accuracyModifier": -0.05,
        "recoilModifier": -0.06,
        "lightBleedModifier": 0,
        "heavyBleedModifier": 0,
        "fragmentationChance": 0.15,
        "initialSpeed": 365,
        "tracer": true,
        "tracerColor": "tracerGreen",
        "ammoType": "bullet",
        "projectileCount": 1
      },
      {
        "caliber": "Caliber9x19PARA",
        "damage": 52,
        "penetrationPower": 30,
        "armorDamage": 48,
        "accuracyModifier": 0,
        "recoilModifier": 0,
        "lightBleedModifier": 0,
        "heavyBleedModifier": 0,
        "fragmentationChance": 0.05,
        "initialSpeed": 392,
        "tracer": false,
        "tracerColor": "red",
        "ammoType": "bullet",
        "projectileCount": 1
      },
      {
        "caliber": "Caliber127x55",
        "damage": 115,
        "penetrationPower": 28,
        "armorDamage": 60,
        "accuracyModifier": 0.1,
        "recoilModifier": 0,
        "lightBleedModifier": 0.3,
        "heavyBleedModifier": 0.2,
        "fragmentationChance": 0.3,
        "initialSpeed": 285,
        "tracer": false,
        "tracerColor": "red",
        "ammoType": "bullet",
        "projectileCount": 1
      },
      {
        "caliber": "Caliber127x55",
        "damage": 165,
        "penetrationPower": 10,
        "armorDamage": 22,
        "accuracyModifier": -0.15,
        "recoilModifier": -0.12,
        "lightBleedModifier": 0.35,
        "heavyBleedModifier": 0.3,
        "fragmentationChance": 0.7,
        "initialSpeed": 290,
        "tracer": false,
        "tracerColor": "red",
        "ammoType": "bullet",
        "projectileCount": 1
      },
      {
        "caliber": "Caliber127x55",
        "damage": 102,
        "penetrationPower": 46,
        "armorDamage": 57,
        "accuracyModifier": 0,
        "recoilModifier": 0.15,
        "lightBleedModifier": 0,
        "heavyBleedModifier": 0.15,
        "fragmentationChance": 0.3,
        "initialSpeed": 300,
        "tracer": false,
        "tracerColor": "red",
        "ammoType": "bullet",
        "projectileCount": 1
      },
      {
        "caliber": "Caliber57x28",
        "damage": 49,
        "penetrationPower": 37,
        "armorDamage": 43,
        "accuracyModifier": 0,
        "recoilModifier": 0,
        "lightBleedModifier": 0,
        "heavyBleedModifier": 0,
        "fragmentationChance": 0.2,
        "initialSpeed": 715,
        "tracer": false,
        "tracerColor": "red",
        "ammoType": "bullet",
        "projectileCount": 1
      },
      {
        "caliber": "Caliber57x28",
        "damage": 53,
        "penetrationPower": 33,
        "armorDamage": 41,
        "accuracyModifier": -0.04,
        "recoilModifier": 0,
        "lightBleedModifier": 0,
        "heavyBleedModifier": 0,
        "fragmentationChance": 0.2,
        "initialSpeed": 715,
        "tracer": true,
        "tracerColor": "red",
        "ammoType": "bullet",
        "projectileCount": 1
      },
      {
        "caliber": "Caliber57x28",
        "damage": 59,
        "penetrationPower": 27,
        "armorDamage": 37,
        "accuracyModifier": 0.05,
        "recoilModifier": -0.15,
        "lightBleedModifier": 0,
        "heavyBleedModifier": 0,
        "fragmentationChance": 0.35,
        "initialSpeed": 299,
        "tracer": false,
        "tracerColor": "red",
        "ammoType": "bullet",
        "projectileCount": 1
      },
      {
        "caliber": "Caliber57x28",
        "damage": 70,
        "penetrationPower": 17,
        "armorDamage": 19,
        "accuracyModifier": 0,
        "recoilModifier": 0,
        "lightBleedModifier": 0,
        "heavyBleedModifier": 0,
        "fragmentationChance": 0.8,
        "initialSpeed": 792,
        "tracer": false,
        "tracerColor": "red",
        "ammoType": "bullet",
        "projectileCount": 1
      },
      {
        "caliber": "Caliber57x28",
        "damage": 62,
        "penetrationPower": 25,
        "armorDamage": 22,
        "accuracyModifier": 0.1,
        "recoilModifier": 0,
        "lightBleedModifier": 0,
        "heavyBleedModifier": 0,
        "fragmentationChance": 0.5,
        "initialSpeed": 594,
        "tracer": false,
        "tracerColor": "red",
        "ammoType": "bullet",
        "projectileCount": 1
      },
      {
        "caliber": "Caliber57x28",
        "damage": 98,
        "penetrationPower": 8,
        "armorDamage": 7,
        "accuracyModifier": 0,
        "recoilModifier": 0,
        "lightBleedModifier": 0.2,
        "heavyBleedModifier": 0.2,
        "fragmentationChance": 1,
        "initialSpeed": 729,
        "tracer": false,
        "tracerColor": "red",
        "ammoType": "bullet",
        "projectileCount": 1
      },
      {
        "caliber": "Caliber57x28",
        "damage": 81,
        "penetrationPower": 11,
        "armorDamage": 9,
        "accuracyModifier": -0.05,
        "recoilModifier": 0,
        "lightBleedModifier": 0.1,
        "heavyBleedModifier": 0.1,
        "fragmentationChance": 0.7,
        "initialSpeed": 724,
        "tracer": false,
        "tracerColor": "red",
        "ammoType": "bullet",
        "projectileCount": 1
      },
      {
        "caliber": "Caliber12g",
        "damage": 37,
        "penetrationPower": 1,
        "armorDamage": 15,
        "accuracyModifier": 0,
        "recoilModifier": 0,
        "lightBleedModifier": 0,
        "heavyBleedModifier": 0,
        "fragmentationChance": 0,
        "initialSpeed": 330,
        "tracer": false,
        "tracerColor": "red",
        "ammoType": "buckshot",
        "projectileCount": 8
      },
      {
        "caliber": "Caliber12g",
        "damage": 35,
        "penetrationPower": 3,
        "armorDamage": 26,
        "accuracyModifier": 0.15,
        "recoilModifier": 0,
        "lightBleedModifier": 0,
        "heavyBleedModifier": 0,
        "fragmentationChance": 0,
        "initialSpeed": 430,
        "tracer": false,
        "tracerColor": "red",
        "ammoType": "buckshot",
        "projectileCount": 9
      },
      {
        "caliber": "Caliber12g",
        "damage": 50,
        "penetrationPower": 2,
        "armorDamage": 26,
        "accuracyModifier": -0.15,
        "recoilModifier": 1.15,
        "lightBleedModifier": 0.2,
        "heavyBleedModifier": 0.1,
        "fragmentationChance": 0,
        "initialSpeed": 385,
        "tracer": false,
        "tracerColor": "red",
        "ammoType": "buckshot",
        "projectileCount": 8
      },
      {
        "caliber": "Caliber12g",
        "damage": 190,
        "penetrationPower": 12,
        "armorDamage": 48,
        "accuracyModifier": 0.8,
        "recoilModifier": 0.2,
        "lightBleedModifier": 0,
        "heavyBleedModifier": 0.1,
        "fragmentationChance": 0.12,
        "initialSpeed": 390,
        "tracer": false,
        "tracerColor": "red",
        "ammoType": "bullet",
        "projectileCount": 1
      },
      {
        "caliber": "Caliber12g",
        "damage": 140,
        "penetrationPower": 17,
        "armorDamage": 40,
        "accuracyModifier": 1.1,
        "recoilModifier": -0.15,
        "lightBleedModifier": 0,
        "heavyBleedModifier": 0,
        "fragmentationChance": 0.2,
        "initialSpeed": 410,
        "tracer": false,
        "tracerColor": "red",
        "ammoType": "bullet",
        "projectileCount": 1
      },
      {
        "caliber": "Caliber12g",
        "damage": 150,
        "penetrationPower": 20,
        "armorDamage": 50,
        "accuracyModifier": 1.15,
        "recoilModifier": -0.1,
        "lightBleedModifier": 0,
        "heavyBleedModifier": 0.05,
        "fragmentationChance": 0.15,
        "initialSpeed": 430,
        "tracer": false,
        "tracerColor": "red",
        "ammoType": "bullet",
        "projectileCount": 1
      },
      {
        "caliber": "Caliber12g",
        "damage": 164,
        "penetrationPower": 37,
        "armorDamage": 65,
        "accuracyModifier": 0.8,
        "recoilModifier": 0.5,
        "lightBleedModifier": 0,
        "heavyBleedModifier": 0.1,
        "fragmentationChance": 0.03,
        "initialSpeed": 510,
        "tracer": false,
        "tracerColor": "red",
        "ammoType": "bullet",
        "projectileCount": 1
      },
      {
        "caliber": "Caliber12g",
        "damage": 206,
        "penetrationPower": 14,
        "armorDamage": 46,
        "accuracyModifier": 1.5,
        "recoilModifier": 0.1,
        "lightBleedModifier": 0.35,
        "heavyBleedModifier": 0.25,
        "fragmentationChance": 0.38,
        "initialSpeed": 442,
        "tracer": false,
        "tracerColor": "red",
        "ammoType": "bullet",
        "projectileCount": 1
      },
      {
        "caliber": "Caliber12g",
        "damage": 197,
        "penetrationPower": 26,
        "armorDamage": 57,
        "accuracyModifier": 0.9,
        "recoilModifier": 0.25,
        "lightBleedModifier": 0,
        "heavyBleedModifier": 0.15,
        "fragmentationChance": 0.05,
        "initialSpeed": 410,
        "tracer": false,
        "tracerColor": "red",
        "ammoType": "bullet",
        "projectileCount": 1
      },
      {
        "caliber": "Caliber12g",
        "damage": 220,
        "penetrationPower": 5,
        "armorDamage": 12,
        "accuracyModifier": 1.7,
        "recoilModifier": -0.15,
        "lightBleedModifier": 0.3,
        "heavyBleedModifier": 0.4,
        "fragmentationChance": 0.39,
        "initialSpeed": 594,
        "tracer": false,
        "tracerColor": "red",
        "ammoType": "bullet",
        "projectileCount": 1
      },
      {
        "caliber": "Caliber12g",
        "damage": 85,
        "penetrationPower": 17,
        "armorDamage": 65,
        "accuracyModifier": 1,
        "recoilModifier": 0.15,
        "lightBleedModifier": 0,
        "heavyBleedModifier": 0.15,
        "fragmentationChance": 0.1,
        "initialSpeed": 415,
        "tracer": false,
        "tracerColor": "red",
        "ammoType": "bullet",
        "projectileCount": 2
      },
      {
        "caliber": "Caliber12g",
        "damage": 183,
        "penetrationPower": 20,
        "armorDamage": 50,
        "accuracyModifier": 1.35,
        "recoilModifier": -0.25,
        "lightBleedModifier": 0,
        "heavyBleedModifier": 0,
        "fragmentationChance": 0.1,
        "initialSpeed": 480,
        "tracer": false,
        "tracerColor": "red",
        "ammoType": "bullet",
        "projectileCount": 1
      },
      {
        "caliber": "Caliber12g",
        "damage": 25,
        "penetrationPower": 31,
        "armorDamage": 26,
        "accuracyModifier": -0.1,
        "recoilModifier": 0,
        "lightBleedModifier": 0.25,
        "heavyBleedModifier": 0.25,
        "fragmentationChance": 0,
        "initialSpeed": 320,
        "tracer": false,
        "tracerColor": "red",
        "ammoType": "buckshot",
        "projectileCount": 8
      },
      {
        "caliber": "Caliber20g",
        "damage": 26,
        "penetrationPower": 1,
        "armorDamage": 12,
        "accuracyModifier": -0.1,
        "recoilModifier": 0.1,
        "lightBleedModifier": 0,
        "heavyBleedModifier": 0,
        "fragmentationChance": 0,
        "initialSpeed": 340,
        "tracer": false,
        "tracerColor": "red",
        "ammoType": "buckshot",
        "projectileCount": 8
      },
      {
        "caliber": "Caliber20g",
        "damage": 22,
        "penetrationPower": 2,
        "armorDamage": 13,
        "accuracyModifier": 0,
        "recoilModifier": 0,
        "lightBleedModifier": 0,
        "heavyBleedModifier": 0,
        "fragmentationChance": 0,
        "initialSpeed": 410,
        "tracer": false,
        "tracerColor": "red",
        "ammoType": "buckshot",
        "projectileCount": 8
      },
      {
        "caliber": "Caliber20g",
        "damage": 23,
        "penetrationPower": 3,
        "armorDamage": 13,
        "accuracyModifier": 0,
        "recoilModifier": 0.15,
        "lightBleedModifier": 0,
        "heavyBleedModifier": 0,
        "fragmentationChance": 0,
        "initialSpeed": 475,
        "tracer": false,
        "tracerColor": "red",
        "ammoType": "buckshot",
        "projectileCount": 9
      },
      {
        "caliber": "Caliber20g",
        "damage": 154,
        "penetrationPower": 16,
        "armorDamage": 42,
        "accuracyModifier": 1.3,
        "recoilModifier": 0.05,
        "lightBleedModifier": 0,
        "heavyBleedModifier": 0.3,
        "fragmentationChance": 0.1,
        "initialSpeed": 415,
        "tracer": false,
        "tracerColor": "red",
        "ammoType": "bullet",
        "projectileCount": 1
      },
      {
        "caliber": "Caliber20g",
        "damage": 135,
        "penetrationPower": 17,
        "armorDamage": 40,
        "accuracyModifier": 1.1,
        "recoilModifier": -0.1,
        "lightBleedModifier": 0,
        "heavyBleedModifier": 0.1,
        "fragmentationChance": 0.15,
        "initialSpeed": 445,
        "tracer": false,
        "tracerColor": "red",
        "ammoType": "bullet",
        "projectileCount": 1
      },
      {
        "caliber": "Caliber20g",
        "damage": 120,
        "penetrationPower": 14,
        "armorDamage": 35,
        "accuracyModifier": 1.1,
        "recoilModifier": -0.15,
        "lightBleedModifier": 0,
        "heavyBleedModifier": 0,
        "fragmentationChance": 0.2,
        "initialSpeed": 425,
        "tracer": false,
        "tracerColor": "red",
        "ammoType": "bullet",
        "projectileCount": 1
      },
      {
        "caliber": "Caliber20g",
        "damage": 198,
        "penetrationPower": 5,
        "armorDamage": 13,
        "accuracyModifier": 1.25,
        "recoilModifier": 0.3,
        "lightBleedModifier": 0.2,
        "heavyBleedModifier": 0.3,
        "fragmentationChance": 1,
        "initialSpeed": 405,
        "tracer": false,
        "tracerColor": "red",
        "ammoType": "bullet",
        "projectileCount": 1
      },
      {
        "caliber": "Caliber762x54R",
        "damage": 82,
        "penetrationPower": 41,
        "armorDamage": 83,
        "accuracyModifier": -0.01,
        "recoilModifier": -0.05,
        "lightBleedModifier": 0,
        "heavyBleedModifier": 0,
        "fragmentationChance": 0.18,
        "initialSpeed": 800,
        "tracer": true,
        "tracerColor": "green",
        "ammoType": "bullet",
        "projectileCount": 1
      },
      {
        "caliber": "Caliber762x54R",
        "damage": 78,
        "penetrationPower": 55,
        "armorDamage": 87,
        "accuracyModifier": -0.02,
        "recoilModifier": -0.04,
        "lightBleedModifier": 0,
        "heavyBleedModifier": 0,
        "fragmentationChance": 0.081,
        "initialSpeed": 875,
        "tracer": true,
        "tracerColor": "green",
        "ammoType": "bullet",
        "projectileCount": 1
      },
      {
        "caliber": "Caliber762x54R",
        "damage": 72,
        "penetrationPower": 70,
        "armorDamage": 88,
        "accuracyModifier": 0,
        "recoilModifier": 0,
        "lightBleedModifier": 0,
        "heavyBleedModifier": 0,
        "fragmentationChance": 0.083,
        "initialSpeed": 785,
        "tracer": false,
        "tracerColor": "red",
        "ammoType": "bullet",
        "projectileCount": 1
      },
      {
        "caliber": "Caliber762x51",
        "damage": 83,
        "penetrationPower": 35,
        "armorDamage": 42,
        "accuracyModifier": -0.07,
        "recoilModifier": 0,
        "lightBleedModifier": 0,
        "heavyBleedModifier": 0,
        "fragmentationChance": 0.2,
        "initialSpeed": 840,
        "tracer": false,
        "tracerColor": "red",
        "ammoType": "bullet",
        "projectileCount": 1
      },
      {
        "caliber": "Caliber762x51",
        "damage": 87,
        "penetrationPower": 30,
        "armorDamage": 25,
        "accuracyModifier": -0.02,
        "recoilModifier": -0.03,
        "lightBleedModifier": 0.12,
        "heavyBleedModifier": 0.12,
        "fragmentationChance": 0.35,
        "initialSpeed": 808,
        "tracer": false,
        "tracerColor": "red",
        "ammoType": "bullet",
        "projectileCount": 1
      },
      {
        "caliber": "Caliber762x51",
        "damage": 107,
        "penetrationPower": 15,
        "armorDamage": 20,
        "accuracyModifier": 0.1,
        "recoilModifier": -0.05,
        "lightBleedModifier": 0.2,
        "heavyBleedModifier": 0.2,
        "fragmentationChance": 0.7,
        "initialSpeed": 822,
        "tracer": false,
        "tracerColor": "red",
        "ammoType": "bullet",
        "projectileCount": 1
      },
      {
        "caliber": "Caliber1143x23ACP",
        "damage": 72,
        "penetrationPower": 25,
        "armorDamage": 36,
        "accuracyModifier": 0,
        "recoilModifier": 0,
        "lightBleedModifier": 0,
        "heavyBleedModifier": 0,
        "fragmentationChance": 0.01,
        "initialSpeed": 340,
        "tracer": false,
        "tracerColor": "red",
        "ammoType": "bullet",
        "projectileCount": 1
      },
      {
        "caliber": "Caliber23x75",
        "damage": 87,
        "penetrationPower": 11,
        "armorDamage": 20,
        "accuracyModifier": 0,
        "recoilModifier": 0,
        "lightBleedModifier": 0,
        "heavyBleedModifier": 0,
        "fragmentationChance": 0,
        "initialSpeed": 270,
        "tracer": false,
        "tracerColor": "red",
        "ammoType": "buckshot",
        "projectileCount": 8
      },
      {
        "caliber": "Caliber23x75",
        "damage": 0,
        "penetrationPower": 0,
        "armorDamage": 0,
        "accuracyModifier": 0,
        "recoilModifier": 0.2,
        "lightBleedModifier": 0,
        "heavyBleedModifier": 0,
        "fragmentationChance": 0.3,
        "initialSpeed": 80,
        "tracer": false,
        "tracerColor": "red",
        "ammoType": "flashbang",
        "projectileCount": 1
      },
      {
        "caliber": "Caliber23x75",
        "damage": 192,
        "penetrationPower": 39,
        "armorDamage": 75,
        "accuracyModifier": -0.05,
        "recoilModifier": 0.25,
        "lightBleedModifier": 0,
        "heavyBleedModifier": 0,
        "fragmentationChance": 0.2,
        "initialSpeed": 420,
        "tracer": false,
        "tracerColor": "red",
        "ammoType": "bullet",
        "projectileCount": 1
      },
      {
        "caliber": "Caliber1143x23ACP",
        "damage": 130,
        "penetrationPower": 3,
        "armorDamage": 12,
        "accuracyModifier": -0.05,
        "recoilModifier": 0,
        "lightBleedModifier": 0.3,
        "heavyBleedModifier": 0.2,
        "fragmentationChance": 1,
        "initialSpeed": 293,
        "tracer": false,
        "tracerColor": "red",
        "ammoType": "bullet",
        "projectileCount": 1
      },
      {
        "caliber": "Caliber40x46",
        "damage": 199,
        "penetrationPower": 1,
        "armorDamage": 95,
        "accuracyModifier": 0.15,
        "recoilModifier": -0.1,
        "lightBleedModifier": 0,
        "heavyBleedModifier": 0,
        "fragmentationChance": 0,
        "initialSpeed": 76,
        "tracer": false,
        "tracerColor": "green",
        "ammoType": "grenade",
        "projectileCount": 1
      },
      {
        "caliber": "Caliber40x46",
        "damage": 199,
        "penetrationPower": 1,
        "armorDamage": 95,
        "accuracyModifier": 0,
        "recoilModifier": 0,
        "lightBleedModifier": 0,
        "heavyBleedModifier": 0,
        "fragmentationChance": 0,
        "initialSpeed": 76,
        "tracer": false,
        "tracerColor": "green",
        "ammoType": "grenade",
        "projectileCount": 1
      },
      {
        "caliber": "Caliber40x46",
        "damage": 199,
        "penetrationPower": 1,
        "armorDamage": 95,
        "accuracyModifier": 0,
        "recoilModifier": 0,
        "lightBleedModifier": 0,
        "heavyBleedModifier": 0,
        "fragmentationChance": 0,
        "initialSpeed": 76,
        "tracer": false,
        "tracerColor": "green",
        "ammoType": "grenade",
        "projectileCount": 1
      },
      {
        "caliber": "Caliber40x46",
        "damage": 160,
        "penetrationPower": 5,
        "armorDamage": 95,
        "accuracyModifier": 1,
        "recoilModifier": 0,
        "lightBleedModifier": 0,
        "heavyBleedModifier": 0,
        "fragmentationChance": 0,
        "initialSpeed": 269,
        "tracer": false,
        "tracerColor": "green",
        "ammoType": "buckshot",
        "projectileCount": 15
      },
      {
        "caliber": "Caliber40x46",
        "damage": 199,
        "penetrationPower": 1,
        "armorDamage": 95,
        "accuracyModifier": 0,
        "recoilModifier": 0,
        "lightBleedModifier": 0,
        "heavyBleedModifier": 0,
        "fragmentationChance": 0,
        "initialSpeed": 76,
        "tracer": false,
        "tracerColor": "green",
        "ammoType": "grenade",
        "projectileCount": 1
      },
      {
        "caliber": "Caliber762x51",
        "damage": 67,
        "penetrationPower": 70,
        "armorDamage": 85,
        "accuracyModifier": 0.05,
        "recoilModifier": 0.08,
        "lightBleedModifier": 0,
        "heavyBleedModifier": 0,
        "fragmentationChance": 0.13,
        "initialSpeed": 910,
        "tracer": false,
        "tracerColor": "red",
        "ammoType": "bullet",
        "projectileCount": 1
      },
      {
        "caliber": "Caliber1143x23ACP",
        "damage": 66,
        "penetrationPower": 38,
        "armorDamage": 48,
        "accuracyModifier": -0.05,
        "recoilModifier": 0.07,
        "lightBleedModifier": 0,
        "heavyBleedModifier": 0,
        "fragmentationChance": 0.01,
        "initialSpeed": 299,
        "tracer": false,
        "tracerColor": "red",
        "ammoType": "bullet",
        "projectileCount": 1
      },
      {
        "caliber": "Caliber1143x23ACP",
        "damage": 76,
        "penetrationPower": 19,
        "armorDamage": 37,
        "accuracyModifier": 0.1,
        "recoilModifier": 0,
        "lightBleedModifier": 0,
        "heavyBleedModifier": 0,
        "fragmentationChance": 0.01,
        "initialSpeed": 290,
        "tracer": true,
        "tracerColor": "red",
        "ammoType": "bullet",
        "projectileCount": 1
      },
      {
        "caliber": "Caliber9x19PARA",
        "damage": 52,
        "penetrationPower": 39,
        "armorDamage": 55,
        "accuracyModifier": 0.05,
        "recoilModifier": 0.05,
        "lightBleedModifier": 0,
        "heavyBleedModifier": 0,
        "fragmentationChance": 0.05,
        "initialSpeed": 560,
        "tracer": false,
        "tracerColor": "red",
        "ammoType": "bullet",
        "projectileCount": 1
      },
      {
        "caliber": "Caliber9x19PARA",
        "damage": 85,
        "penetrationPower": 8,
        "armorDamage": 22,
        "accuracyModifier": 0.1,
        "recoilModifier": 0.1,
        "lightBleedModifier": 0.15,
        "heavyBleedModifier": 0.22,
        "fragmentationChance": 0.1,
        "initialSpeed": 290,
        "tracer": false,
        "tracerColor": "red",
        "ammoType": "bullet",
        "projectileCount": 1
      },
      {
        "caliber": "Caliber1143x23ACP",
        "damage": 100,
        "penetrationPower": 13,
        "armorDamage": 30,
        "accuracyModifier": 0,
        "recoilModifier": 0,
        "lightBleedModifier": 0,
        "heavyBleedModifier": 0.3,
        "fragmentationChance": 0.5,
        "initialSpeed": 274,
        "tracer": false,
        "tracerColor": "red",
        "ammoType": "bullet",
        "projectileCount": 1
      },
      {
        "caliber": "Caliber366TKM",
        "damage": 90,
        "penetrationPower": 42,
        "armorDamage": 60,
        "accuracyModifier": -0.28,
        "recoilModifier": 0.35,
        "lightBleedModifier": 0,
        "heavyBleedModifier": 0.1,
        "fragmentationChance": 0.01,
        "initialSpeed": 602,
        "tracer": false,
        "tracerColor": "red",
        "ammoType": "bullet",
        "projectileCount": 1
      },
      {
        "caliber": "Caliber40x46",
        "damage": 199,
        "penetrationPower": 1,
        "armorDamage": 95,
        "accuracyModifier": 0,
        "recoilModifier": 0,
        "lightBleedModifier": 0,
        "heavyBleedModifier": 0,
        "fragmentationChance": 0,
        "initialSpeed": 76,
        "tracer": false,
        "tracerColor": "green",
        "ammoType": "grenade",
        "projectileCount": 1
      },
      {
        "caliber": "Caliber23x75",
        "damage": 78,
        "penetrationPower": 10,
        "armorDamage": 20,
        "accuracyModifier": 0.2,
        "recoilModifier": 0.1,
        "lightBleedModifier": 0,
        "heavyBleedModifier": 0,
        "fragmentationChance": 0,
        "initialSpeed": 375,
        "tracer": false,
        "tracerColor": "red",
        "ammoType": "buckshot",
        "projectileCount": 8
      },
      {
        "caliber": "Caliber762x35",
        "damage": 60,
        "penetrationPower": 30,
        "armorDamage": 36,
        "accuracyModifier": 0,
        "recoilModifier": 0,
        "lightBleedModifier": 0,
        "heavyBleedModifier": 0,
        "fragmentationChance": 0.3,
        "initialSpeed": 605,
        "tracer": false,
        "tracerColor": "red",
        "ammoType": "bullet",
        "projectileCount": 1
      },
      {
        "caliber": "Caliber86x70",
        "damage": 122,
        "penetrationPower": 47,
        "armorDamage": 83,
        "accuracyModifier": 0,
        "recoilModifier": 0,
        "lightBleedModifier": 0.35,
        "heavyBleedModifier": 0.5,
        "fragmentationChance": 0.2,
        "initialSpeed": 900,
        "tracer": false,
        "tracerColor": "red",
        "ammoType": "bullet",
        "projectileCount": 1
      },
      {
        "caliber": "Caliber86x70",
        "damage": 115,
        "penetrationPower": 79,
        "armorDamage": 89,
        "accuracyModifier": 0,
        "recoilModifier": 0.1,
        "lightBleedModifier": 0.2,
        "heavyBleedModifier": 0.55,
        "fragmentationChance": 0.13,
        "initialSpeed": 849,
        "tracer": false,
        "tracerColor": "red",
        "ammoType": "bullet",
        "projectileCount": 1
      },
      {
        "caliber": "Caliber86x70",
        "damage": 196,
        "penetrationPower": 18,
        "armorDamage": 55,
        "accuracyModifier": 0.1,
        "recoilModifier": -0.05,
        "lightBleedModifier": 0.8,
        "heavyBleedModifier": 0.5,
        "fragmentationChance": 0.5,
        "initialSpeed": 880,
        "tracer": false,
        "tracerColor": "red",
        "ammoType": "bullet",
        "projectileCount": 1
      },
      {
        "caliber": "Caliber86x70",
        "damage": 142,
        "penetrationPower": 32,
        "armorDamage": 70,
        "accuracyModifier": -0.05,
        "recoilModifier": 0,
        "lightBleedModifier": 0.5,
        "heavyBleedModifier": 0.4,
        "fragmentationChance": 0.6,
        "initialSpeed": 849,
        "tracer": false,
        "tracerColor": "red",
        "ammoType": "bullet",
        "projectileCount": 1
      },
      {
        "caliber": "Caliber762x35",
        "damage": 51,
        "penetrationPower": 48,
        "armorDamage": 65,
        "accuracyModifier": 0,
        "recoilModifier": 0.03,
        "lightBleedModifier": 0.15,
        "heavyBleedModifier": 0.15,
        "fragmentationChance": 0.1,
        "initialSpeed": 635,
        "tracer": false,
        "tracerColor": "red",
        "ammoType": "bullet",
        "projectileCount": 1
      },
      {
        "caliber": "Caliber556x45NATO",
        "damage": 55,
        "penetrationPower": 33,
        "armorDamage": 39,
        "accuracyModifier": 0.02,
        "recoilModifier": 0.03,
        "lightBleedModifier": 0.15,
        "heavyBleedModifier": 0.1,
        "fragmentationChance": 0.35,
        "initialSpeed": 902,
        "tracer": false,
        "tracerColor": "red",
        "ammoType": "bullet",
        "projectileCount": 1
      },
      {
        "caliber": "Caliber556x45NATO",
        "damage": 38,
        "penetrationPower": 57,
        "armorDamage": 58,
        "accuracyModifier": -0.09,
        "recoilModifier": 0.06,
        "lightBleedModifier": 0,
        "heavyBleedModifier": 0,
        "fragmentationChance": 0.3,
        "initialSpeed": 1013,
        "tracer": false,
        "tracerColor": "red",
        "ammoType": "bullet",
        "projectileCount": 1
      },
      {
        "caliber": "Caliber762x39",
        "damage": 47,
        "penetrationPower": 58,
        "armorDamage": 76,
        "accuracyModifier": -0.05,
        "recoilModifier": 0.1,
        "lightBleedModifier": 0.1,
        "heavyBleedModifier": 0.1,
        "fragmentationChance": 0.05,
        "initialSpeed": 875,
        "tracer": false,
        "tracerColor": "red",
        "ammoType": "bullet",
        "projectileCount": 1
      },
      {
        "caliber": "Caliber545x39",
        "damage": 52,
        "penetrationPower": 42,
        "armorDamage": 45,
        "accuracyModifier": 0.5,
        "recoilModifier": -0.1,
        "lightBleedModifier": 0.2,
        "heavyBleedModifier": 0.15,
        "fragmentationChance": 0.02,
        "initialSpeed": 915,
        "tracer": false,
        "tracerColor": "red",
        "ammoType": "bullet",
        "projectileCount": 1
      },
      {
        "caliber": "Caliber9x39",
        "damage": 62,
        "penetrationPower": 43,
        "armorDamage": 57,
        "accuracyModifier": -0.15,
        "recoilModifier": 0.1,
        "lightBleedModifier": 0.1,
        "heavyBleedModifier": 0.12,
        "fragmentationChance": 0.1,
        "initialSpeed": 320,
        "tracer": false,
        "tracerColor": "red",
        "ammoType": "bullet",
        "projectileCount": 1
      },
      {
        "caliber": "Caliber762x35",
        "damage": 72,
        "penetrationPower": 20,
        "armorDamage": 25,
        "accuracyModifier": 0.3,
        "recoilModifier": -0.1,
        "lightBleedModifier": 0.22,
        "heavyBleedModifier": 0,
        "fragmentationChance": 0.25,
        "initialSpeed": 723,
        "tracer": false,
        "tracerColor": "red",
        "ammoType": "bullet",
        "projectileCount": 1
      },
      {
        "caliber": "Caliber762x35",
        "damage": 90,
        "penetrationPower": 14,
        "armorDamage": 18,
        "accuracyModifier": 0.05,
        "recoilModifier": -0.05,
        "lightBleedModifier": 0,
        "heavyBleedModifier": 0.2,
        "fragmentationChance": 0.35,
        "initialSpeed": 853,
        "tracer": false,
        "tracerColor": "red",
        "ammoType": "bullet",
        "projectileCount": 1
      },
      {
        "caliber": "Caliber762x35",
        "damage": 54,
        "penetrationPower": 36,
        "armorDamage": 40,
        "accuracyModifier": 0,
        "recoilModifier": 0.01,
        "lightBleedModifier": 0,
        "heavyBleedModifier": 0,
        "fragmentationChance": 0.2,
        "initialSpeed": 442,
        "tracer": true,
        "tracerColor": "red",
        "ammoType": "bullet",
        "projectileCount": 1
      },
      {
        "caliber": "Caliber9x33R",
        "damage": 70,
        "penetrationPower": 35,
        "armorDamage": 43,
        "accuracyModifier": 0,
        "recoilModifier": 0.12,
        "lightBleedModifier": 0,
        "heavyBleedModifier": 0.1,
        "fragmentationChance": 0.01,
        "initialSpeed": 385,
        "tracer": false,
        "tracerColor": "red",
        "ammoType": "bullet",
        "projectileCount": 1
      },
      {
        "caliber": "Caliber9x33R",
        "damage": 99,
        "penetrationPower": 18,
        "armorDamage": 20,
        "accuracyModifier": 0.15,
        "recoilModifier": 0.15,
        "lightBleedModifier": 0.4,
        "heavyBleedModifier": 0.3,
        "fragmentationChance": 0.6,
        "initialSpeed": 481,
        "tracer": false,
        "tracerColor": "red",
        "ammoType": "bullet",
        "projectileCount": 1
      },
      {
        "caliber": "Caliber9x33R",
        "damage": 88,
        "penetrationPower": 24,
        "armorDamage": 28,
        "accuracyModifier": 0.15,
        "recoilModifier": 0.08,
        "lightBleedModifier": 0.25,
        "heavyBleedModifier": 0.25,
        "fragmentationChance": 0.6,
        "initialSpeed": 425,
        "tracer": false,
        "tracerColor": "red",
        "ammoType": "bullet",
        "projectileCount": 1
      },
      {
        "caliber": "Caliber9x33R",
        "damage": 108,
        "penetrationPower": 12,
        "armorDamage": 15,
        "accuracyModifier": 0.27,
        "recoilModifier": -0.29,
        "lightBleedModifier": 0.35,
        "heavyBleedModifier": 0.2,
        "fragmentationChance": 0.2,
        "initialSpeed": 455,
        "tracer": false,
        "tracerColor": "red",
        "ammoType": "bullet",
        "projectileCount": 1
      },
      {
        "caliber": "Caliber26x75",
        "damage": 37,
        "penetrationPower": 0,
        "armorDamage": 60,
        "accuracyModifier": 0,
        "recoilModifier": 0,
        "lightBleedModifier": 0,
        "heavyBleedModifier": 0,
        "fragmentationChance": 0,
        "initialSpeed": 80,
        "tracer": true,
        "tracerColor": "yellow",
        "ammoType": "bullet",
        "projectileCount": 1
      },
      {
        "caliber": "Caliber26x75",
        "damage": 37,
        "penetrationPower": 0,
        "armorDamage": 60,
        "accuracyModifier": 0,
        "recoilModifier": 0,
        "lightBleedModifier": 0,
        "heavyBleedModifier": 0,
        "fragmentationChance": 0,
        "initialSpeed": 80,
        "tracer": true,
        "tracerColor": "yellow",
        "ammoType": "bullet",
        "projectileCount": 1
      },
      {
        "caliber": "Caliber26x75",
        "damage": 37,
        "penetrationPower": 0,
        "armorDamage": 60,
        "accuracyModifier": 0,
        "recoilModifier": 0,
        "lightBleedModifier": 0,
        "heavyBleedModifier": 0,
        "fragmentationChance": 0,
        "initialSpeed": 80,
        "tracer": true,
        "tracerColor": "yellow",
        "ammoType": "bullet",
        "projectileCount": 1
      },
      {
        "caliber": "Caliber26x75",
        "damage": 37,
        "penetrationPower": 0,
        "armorDamage": 60,
        "accuracyModifier": 0,
        "recoilModifier": 0,
        "lightBleedModifier": 0,
        "heavyBleedModifier": 0,
        "fragmentationChance": 0,
        "initialSpeed": 80,
        "tracer": true,
        "tracerColor": "yellow",
        "ammoType": "bullet",
        "projectileCount": 1
      },
      {
        "caliber": "Caliber26x75",
        "damage": 37,
        "penetrationPower": 0,
        "armorDamage": 60,
        "accuracyModifier": 0,
        "recoilModifier": 0,
        "lightBleedModifier": 0,
        "heavyBleedModifier": 0,
        "fragmentationChance": 0,
        "initialSpeed": 80,
        "tracer": true,
        "tracerColor": "yellow",
        "ammoType": "bullet",
        "projectileCount": 1
      },
      {
        "caliber": "Caliber46x30",
        "damage": 46,
        "penetrationPower": 32,
        "armorDamage": 37,
        "accuracyModifier": 0,
        "recoilModifier": 0,
        "lightBleedModifier": 0,
        "heavyBleedModifier": 0,
        "fragmentationChance": 0.3,
        "initialSpeed": 579,
        "tracer": false,
        "tracerColor": "red",
        "ammoType": "bullet",
        "projectileCount": 1
      },
      {
        "caliber": "Caliber762x39",
        "damage": 55,
        "penetrationPower": 41,
        "armorDamage": 57,
        "accuracyModifier": -0.01,
        "recoilModifier": 0.05,
        "lightBleedModifier": 0,
        "heavyBleedModifier": 0,
        "fragmentationChance": 0.15,
        "initialSpeed": 732,
        "tracer": false,
        "tracerColor": "red",
        "ammoType": "bullet",
        "projectileCount": 1
      },
      {
        "caliber": "Caliber762x39",
        "damage": 63,
        "penetrationPower": 26,
        "armorDamage": 33,
        "accuracyModifier": 0.02,
        "recoilModifier": -0.02,
        "lightBleedModifier": 0,
        "heavyBleedModifier": 0,
        "fragmentationChance": 0.3,
        "initialSpeed": 775,
        "tracer": false,
        "tracerColor": "red",
        "ammoType": "bullet",
        "projectileCount": 1
      },
      {
        "caliber": "Caliber762x39",
        "damage": 68,
        "penetrationPower": 20,
        "armorDamage": 27,
        "accuracyModifier": 0.05,
        "recoilModifier": -0.05,
        "lightBleedModifier": 0.05,
        "heavyBleedModifier": 0.05,
        "fragmentationChance": 0.35,
        "initialSpeed": 772,
        "tracer": false,
        "tracerColor": "red",
        "ammoType": "bullet",
        "projectileCount": 1
      },
      {
        "caliber": "Caliber9x19PARA",
        "damage": 56,
        "penetrationPower": 18,
        "armorDamage": 35,
        "accuracyModifier": 0,
        "recoilModifier": 0,
        "lightBleedModifier": 0,
        "heavyBleedModifier": 0,
        "fragmentationChance": 0.2,
        "initialSpeed": 385,
        "tracer": false,
        "tracerColor": "red",
        "ammoType": "bullet",
        "projectileCount": 1
      },
      {
        "caliber": "Caliber762x35",
        "damage": 58,
        "penetrationPower": 43,
        "armorDamage": 57,
        "accuracyModifier": 0,
        "recoilModifier": 0.05,
        "lightBleedModifier": 0,
        "heavyBleedModifier": 0,
        "fragmentationChance": 0.15,
        "initialSpeed": 725,
        "tracer": false,
        "tracerColor": "red",
        "ammoType": "bullet",
        "projectileCount": 1
      },
      {
        "caliber": "Caliber12g",
        "damage": 25,
        "penetrationPower": 24,
        "armorDamage": 22,
        "accuracyModifier": -0.05,
        "recoilModifier": 0,
        "lightBleedModifier": 0.15,
        "heavyBleedModifier": 0.15,
        "fragmentationChance": 0,
        "initialSpeed": 310,
        "tracer": false,
        "tracerColor": "red",
        "ammoType": "bullet",
        "projectileCount": 10
      },
      {
        "caliber": "Caliber762x54R",
        "damage": 84,
        "penetrationPower": 33,
        "armorDamage": 63,
        "accuracyModifier": 0,
        "recoilModifier": 0,
        "lightBleedModifier": 0,
        "heavyBleedModifier": 0,
        "fragmentationChance": 0.2,
        "initialSpeed": 760,
        "tracer": false,
        "tracerColor": "red",
        "ammoType": "bullet",
        "projectileCount": 1
      },
      {
        "caliber": "Caliber762x54R",
        "damage": 92,
        "penetrationPower": 27,
        "armorDamage": 56,
        "accuracyModifier": 0.07,
        "recoilModifier": 0,
        "lightBleedModifier": 0,
        "heavyBleedModifier": 0,
        "fragmentationChance": 0.24,
        "initialSpeed": 703,
        "tracer": false,
        "tracerColor": "red",
        "ammoType": "bullet",
        "projectileCount": 1
      },
      {
        "caliber": "Caliber762x54R",
        "damage": 102,
        "penetrationPower": 23,
        "armorDamage": 37,
        "accuracyModifier": 0.1,
        "recoilModifier": 0,
        "lightBleedModifier": 0,
        "heavyBleedModifier": 0,
        "fragmentationChance": 0.4,
        "initialSpeed": 807,
        "tracer": false,
        "tracerColor": "red",
        "ammoType": "bullet",
        "projectileCount": 1
      },
      {
        "caliber": "Caliber68x51",
        "damage": 72,
        "penetrationPower": 47,
        "armorDamage": 58,
        "accuracyModifier": 0.03,
        "recoilModifier": 0.1,
        "lightBleedModifier": 0,
        "heavyBleedModifier": 0,
        "fragmentationChance": 0.12,
        "initialSpeed": 914,
        "tracer": false,
        "tracerColor": "red",
        "ammoType": "bullet",
        "projectileCount": 1
      },
      {
        "caliber": "Caliber68x51",
        "damage": 80,
        "penetrationPower": 36,
        "armorDamage": 49,
        "accuracyModifier": 0,
        "recoilModifier": 0,
        "lightBleedModifier": 0,
        "heavyBleedModifier": 0,
        "fragmentationChance": 0.18,
        "initialSpeed": 899,
        "tracer": false,
        "tracerColor": "red",
        "ammoType": "bullet",
        "projectileCount": 1
      },
      {
        "caliber": "Caliber9x21",
        "damage": 45,
        "penetrationPower": 38,
        "armorDamage": 47,
        "accuracyModifier": -0.03,
        "recoilModifier": 0.1,
        "lightBleedModifier": 0,
        "heavyBleedModifier": 0,
        "fragmentationChance": 0.1,
        "initialSpeed": 400,
        "tracer": false,
        "tracerColor": "red",
        "ammoType": "bullet",
        "projectileCount": 1
      },
      {
        "caliber": "Caliber9x21",
        "damage": 47,
        "penetrationPower": 27,
        "armorDamage": 44,
        "accuracyModifier": 0,
        "recoilModifier": 0,
        "lightBleedModifier": 0,
        "heavyBleedModifier": 0,
        "fragmentationChance": 0.25,
        "initialSpeed": 300,
        "tracer": false,
        "tracerColor": "red",
        "ammoType": "bullet",
        "projectileCount": 1
      },
      {
        "caliber": "Caliber9x39",
        "damage": 75,
        "penetrationPower": 17,
        "armorDamage": 28,
        "accuracyModifier": 0.05,
        "recoilModifier": -0.05,
        "lightBleedModifier": 0,
        "heavyBleedModifier": 0,
        "fragmentationChance": 0.3,
        "initialSpeed": 330,
        "tracer": false,
        "tracerColor": "red",
        "ammoType": "bullet",
        "projectileCount": 1
      },
      {
        "caliber": "Caliber20x1mm",
        "damage": 1,
        "penetrationPower": 0,
        "armorDamage": 0,
        "accuracyModifier": 0,
        "recoilModifier": 0.01,
        "lightBleedModifier": 0,
        "heavyBleedModifier": 0,
        "fragmentationChance": 0,
        "initialSpeed": 20,
        "tracer": false,
        "tracerColor": "red",
        "ammoType": "bullet",
        "projectileCount": 1
      }
    ]
}